rul_adapt/__init__.py
rul_adapt/approach/__init__.py
rul_adapt/approach/abstract.py
rul_adapt/approach/adarul.py
rul_adapt/approach/cnn_dann.py
rul_adapt/approach/conditional.py
rul_adapt/approach/consistency.py
rul_adapt/approach/dann.py
rul_adapt/approach/evaluation.py
rul_adapt/approach/latent_align.py
rul_adapt/approach/mmd.py
rul_adapt/approach/pseudo_labels.py
rul_adapt/approach/supervised.py
rul_adapt/approach/tbigru.py
rul_adapt/construct/__init__.py
rul_adapt/construct/adarul/__init__.py
rul_adapt/construct/adarul/config/base.yaml
rul_adapt/construct/adarul/config/task_source/fd1.yaml
rul_adapt/construct/adarul/config/task_source/fd2.yaml
rul_adapt/construct/adarul/config/task_source/fd3.yaml
rul_adapt/construct/adarul/config/task_source/fd4.yaml
rul_adapt/construct/adarul/functional.py
rul_adapt/construct/cnn_dann/__init__.py
rul_adapt/construct/cnn_dann/config/base.yaml
rul_adapt/construct/cnn_dann/functional.py
rul_adapt/construct/consistency/__init__.py
rul_adapt/construct/consistency/config/base.yaml
rul_adapt/construct/consistency/config/dataset/cmapss.yaml
rul_adapt/construct/consistency/config/dataset/xjtu-sy.yaml
rul_adapt/construct/consistency/functional.py
rul_adapt/construct/latent_align/__init__.py
rul_adapt/construct/latent_align/config/base.yaml
rul_adapt/construct/latent_align/config/dataset/cmapss.yaml
rul_adapt/construct/latent_align/config/dataset/xjtu-sy.yaml
rul_adapt/construct/latent_align/config/split_steps/FD001.yaml
rul_adapt/construct/latent_align/config/split_steps/FD002.yaml
rul_adapt/construct/latent_align/config/split_steps/FD003.yaml
rul_adapt/construct/latent_align/config/split_steps/FD004.yaml
rul_adapt/construct/latent_align/config/subtask/SUB11.yaml
rul_adapt/construct/latent_align/config/subtask/SUB12.yaml
rul_adapt/construct/latent_align/config/subtask/SUB21.yaml
rul_adapt/construct/latent_align/config/subtask/SUB22.yaml
rul_adapt/construct/latent_align/functional.py
rul_adapt/construct/lstm_dann/__init__.py
rul_adapt-0.6.1.dist-info/WHEEL
rul_adapt-0.6.1.dist-info/METADATA
rul_adapt-0.6.1.dist-info/RECORD
