Metadata-Version: 2.1
Name: rul-adapt
Version: 0.6.1
Summary: A collection of unsupervised domain adaption approaches for RUL estimation.
Home-page: https://krokotsch.eu/rul-adapt
License: MIT
Author: Krokotsch, Tilman
Author-email: tilman.krokotsch@tu-berlin.de
Requires-Python: >=3.8,<4.0
Classifier: License :: OSI Approved :: MIT License
Classifier: Programming Language :: Python :: 3
Classifier: Programming Language :: Python :: 3.8
Classifier: Programming Language :: Python :: 3.9
Classifier: Programming Language :: Python :: 3.10
Classifier: Programming Language :: Python :: 3.11
Classifier: Topic :: Scientific/Engineering
Classifier: Topic :: Scientific/Engineering :: Artificial Intelligence
Requires-Dist: dtaidistance (>=2.3.10,<3.0.0)
Requires-Dist: hydra-core (>=1.3.1,<2.0.0)
Requires-Dist: pytorch-lightning (>1.8.0.post1)
Requires-Dist: pywavelets (>=1.4.1,<2.0.0)
Requires-Dist: rul-datasets (>=0.15.0)
Requires-Dist: tqdm (>=4.62.2,<5.0.0)
Project-URL: Repository, https://github.com/tilman151/rul-adapt
